{
  "listA": [
    "пр..небрегать",
    "пр..лестный",
    "пр..зидент",
    "пр..подобный",
    "пр..вередливый",
    "пр..пятствие",
    "пр..следовать",
    "пр..чудливый",
    "пр..пона",
    "пр..смыкаться",
    "непр..ступный",
    "пр..митивный",
    "непр..хотливый",
    "пр..гожий",
    "пр..родный",
    "пр..мьера",
    "пр..парат",
    "пр..тензия",
    "пр..тендент",
    "пр..грешения",
    "пр..имущество",
    "пр..влекательный",
    "пр..вилегия",
    "пр..оритет",
    "пр..ключение",
    "пр..видение",
    "пр..амбула",
    "пр..данность",
    "пр..ступник",
    "пр..чина"
  ],
  "listB": [
    "Е",
    "Е",
    "Е",
    "Е",
    "И",
    "Е",
    "Е",
    "И",
    "Е",
    "И",
    "Е",
    "И",
    "И",
    "И",
    "И",
    "Е",
    "Е",
    "Е",
    "Е",
    "Е",
    "И",
    "И",
    "И",
    "И",
    "И",
    "И",
    "Е",
    "И",
    "Е",
    "И"
  ],
  "freeMode": true,
  "feedback": "Все заклинания восстановлены!",
  "language": "ru",
  "mathMode": false
}