{
  "listA": [
    "https://ltdfoto.ru/images/2026/01/10/1.png",
    "https://ltdfoto.ru/images/2026/01/10/2.png",
    "https://ltdfoto.ru/images/2026/01/10/3.png",
    "https://ltdfoto.ru/images/2026/01/10/4.png",
    "https://ltdfoto.ru/images/2026/01/10/5.png",
    "https://ltdfoto.ru/images/2026/01/10/6.png",
    "https://ltdfoto.ru/images/2026/01/10/7.png",
    "https://ltdfoto.ru/images/2026/01/10/8.png",
    "https://ltdfoto.ru/images/2026/01/10/9.png",
    "https://ltdfoto.ru/images/2026/01/10/12.png",
    "https://ltdfoto.ru/images/2026/01/10/13.png",
    "https://ltdfoto.ru/images/2026/01/10/14.png"
  ],
  "listB": [
    "sing",
    "climb",
    "swim",
    "jump",
    "run",
    "dance",
    "talk",
    "climb",
    "walk",
    "walk",
    "crawl",
    "fly"
  ],
  "freeMode": false,
  "feedback": "Congratulations!",
  "language": "en",
  "mathMode": false
}