{
  "language": "ru",
  "font": "PT Sans",
  "fontSize": 40,
  "textColor": "#ece9df",
  "speed": 3,
  "style": {
    "shape": "rounded",
    "pad": 51,
    "bgColor": "#20431e",
    "bgImages": [],
    "bgImage": "",
    "borderOn": false,
    "borderColor": "#0c794a",
    "borderWidth": 0,
    "shadow": true,
    "glow": false,
    "glowColor": "#e1da0e",
    "fx3d": true,
    "opacity": 1,
    "imgBox": 130
  },
  "randomLevels": false,
  "start": {
    "title": "Отрицательные местоимения",
    "btnText": "Старт"
  },
  "direction": "down",
  "finalFeedback": "Отличная работа!",
  "levels": [
    {
      "target": "отрицательные местоимения",
      "correct": [
        "никто",
        "нигде",
        "никого",
        "нечего",
        "негде",
        "никакой",
        "никакая",
        "никакое",
        "никакие",
        "ничто",
        "ничего",
        "ничей",
        "ничья",
        "ничьи",
        "ничьё"
      ],
      "wrong": [
        "я",
        "ты",
        "он",
        "мне",
        "ему",
        "меня",
        "вы",
        "вас",
        "ваш",
        "о нём",
        "о ней",
        "о них",
        "им",
        "с ними",
        "о нас",
        "у него",
        "они",
        "у них",
        "его",
        "её",
        "вам",
        "нам"
      ],
      "timer": 50
    },
    {
      "target": "Личные местоимения и их формы",
      "correct": [
        "я",
        "ты",
        "он",
        "мне",
        "ему",
        "меня",
        "вы",
        "вас",
        "ваш",
        "о нём",
        "о ней",
        "о них",
        "им",
        "с ними",
        "о нас",
        "у него",
        "они",
        "у них",
        "его",
        "её",
        "вам",
        "нам"
      ],
      "wrong": [
        "никто",
        "нигде",
        "никого",
        "нечего",
        "негде",
        "никакой",
        "никакая",
        "никакое",
        "никакие",
        "ничто",
        "ничего",
        "ничей",
        "ничья",
        "ничьи",
        "ничьё"
      ],
      "timer": 50
    }
  ]
}