{"language":"ru","font":"Nunito","bg":"","sounds":{"correct":"https://nikashum93.github.io/match/correct.mp3","wrong":"https://nikashum93.github.io/match/wrong.mp3","win":"https://nikashum93.github.io/match/win.mp3"},"style":{"animHover":"none","animClick":"none","effMatch":"fireworks","effMismatch":"shake","effMismatchEmoji":"💩","glowColor":"#00fbff","idle":{"target":"both","anim":"none","glowEnabled":false,"glow":"#9cacec","sparksEnabled":false,"sparks":"#fff700"},"matchedOpacity":1,"left":{"bgColor":"#000000","bgOpacity":0.6,"borderColor":"#ffffff","borderWidth":1,"textColor":"#ffffff"},"right":{"bgColor":"#000000","bgOpacity":0.6,"borderColor":"#ffffff","borderWidth":2,"textColor":"#ffffff"},"tooltip":{"bg":"#222222","color":"#00ffcc","glow":"#00ffcc","radius":8},"line":{"enabled":true,"color":"#00ccff","thickness":4,"style":"gradient","emoji":"🟢"},"dot":{"color":"#00ffcc","size":30,"style":"circle"}},"feedback":{"mode":"both","sparks":false,"transparentBg":false,"fbTextGlow":false,"imgGlow":false,"text":"🎉 Отлично! Занимай место в своей КРУЖКЕ!","font":"Nunito","fontSize":28,"textColor":"#ffffff","bgColor":"#0a0a0f","borderColor":"#00bfff","borderWidth":2,"radius":16,"glowColor":"#00b3ff","shadow":"#000000","blur":0,"anim":"zoomIn","img":"https://img.genially.com/685bd5c7a2beff001e0fd0cd/57edddd0-430c-48a2-83a5-f415bac373cf.png","imgX":480,"imgY":100,"imgW":320,"imgH":240,"txtX":440,"txtY":400,"txtW":400,"txtH":150},"items":[{"id":"L0","side":"left","pairIndex":0,"text":"$x^2+8x+16$","img":"","x":198,"y":84,"w":332,"h":69,"rot":0,"fontSize":40,"tooltip":{"text":"","img":""}},{"id":"R0","side":"right","pairIndex":0,"text":"$(x+4)^2$","img":"","x":803,"y":303,"w":227,"h":73,"rot":0,"fontSize":40,"tooltip":{"text":"","img":""}},{"id":"L1","side":"left","pairIndex":1,"text":"$36x^2-12xy+y^2$","img":"","x":194,"y":186,"w":373,"h":77,"rot":0,"fontSize":40,"tooltip":{"text":"","img":""}},{"id":"R1","side":"right","pairIndex":1,"text":"$(6x-y)^2$","img":"","x":804,"y":88,"w":206,"h":62,"rot":0,"fontSize":40,"tooltip":{"text":"","img":""}},{"id":"L2","side":"left","pairIndex":2,"text":"$25+10a+a^2$","img":"","x":197,"y":291,"w":334,"h":68,"rot":0,"fontSize":40,"tooltip":{"text":"","img":""}},{"id":"R2","side":"right","pairIndex":2,"text":"$(5+a)^2$","img":"","x":801,"y":413,"w":232,"h":72,"rot":0,"fontSize":40,"tooltip":{"text":"","img":""}},{"id":"L3","side":"left","pairIndex":3,"text":"$a^2-14ab+49b^2$","img":"","x":192,"y":390,"w":355,"h":85,"rot":0,"fontSize":40,"tooltip":{"text":"","img":""}},{"id":"R3","side":"right","pairIndex":3,"text":"$(a-7b)^2$","img":"","x":807,"y":179,"w":206,"h":75,"rot":0,"fontSize":40,"tooltip":{"text":"","img":""}}]}