{
  "language": "de",
  "font": "PT Sans",
  "fontSize": 24,
  "textColor": "#ffffff",
  "speed": 3,
  "questionFont": "PT Sans",
  "questionFontSize": 26,
  "style": {
    "shape": "rounded",
    "pad": 22,
    "bgColor": "#a3a3a3",
    "bgImage": "",
    "bgImages": [],
    "borderOn": true,
    "borderColor": "#ffffff",
    "borderWidth": 1,
    "shadow": true,
    "glow": false,
    "glowColor": "#00f0ff",
    "fx3d": false,
    "opacity": 1,
    "imgBox": 160
  },
  "randomLevels": false,
  "start": {
    "title": "Max oder Moriz?",
    "btnText": "Los!"
  },
  "direction": "down",
  "finalFeedback": "Toll!",
  "globalTimer": 0,
  "levels": [
    {
      "target": "Max sprach ruhig und __________.",
      "correct": [
        "ernst"
      ],
      "wrong": [
        "wichtig",
        "angenehm",
        "streng"
      ]
    },
    {
      "target": "Die Atmosphäre in Max’ Studio war __________ und sicher.",
      "correct": [
        "angenehm"
      ],
      "wrong": [
        "plötzlich",
        "ernst",
        "sympathisch"
      ]
    },
    {
      "target": "Igor war sehr __________, er erlaubte keine Fehler.",
      "correct": [
        "streng"
      ],
      "wrong": [
        "ernst",
        "wichtig",
        "plötzlich"
      ]
    },
    {
      "target": "Im Studio von Igor war alles __________, niemand fühlte sich wohl.",
      "correct": [
        "chaotisch"
      ],
      "wrong": [
        "angenehm",
        "plötzlich",
        "sympathisch"
      ]
    },
    {
      "target": "__________ kam Igor ins Studio und begann zu schreien.",
      "correct": [
        "plötzlich"
      ],
      "wrong": [
        "wichtig",
        "angenehm",
        "sympathisch"
      ]
    },
    {
      "target": "Max trainierte __________ und kontrolliert.",
      "correct": [
        "sorgfältig"
      ],
      "wrong": [
        "streng",
        "plötzlich",
        "chaotisch"
      ]
    },
    {
      "target": "Viele Menschen fanden Max __________.",
      "correct": [
        "sympathisch"
      ],
      "wrong": [
        "wichtig",
        "angenehm",
        "ernst"
      ]
    },
    {
      "target": "Für Max waren Gefühle __________, nicht nur Muskeln.",
      "correct": [
        "wichtig"
      ],
      "wrong": [
        "chaotisch",
        "sorgfältig",
        "ernst"
      ]
    }
  ]
}