{
  "language": "en",
  "lang": "en",
  "font": "Baloo 2",
  "mode": "input",
  "orderMode": false,
  "lockNext": true,
  "bubbleSize": 100,
  "sounds": {
    "pop": "https://nikashum93.github.io/utki/pop.mp3",
    "open": "https://nikashum93.github.io/utki/open.mp3",
    "correct": "https://nikashum93.github.io/utki/correct.mp3",
    "wrong": ""
  },
  "style": {
    "bgImage": "https://media.tenor.com/mqvTrVZEMxIAAAAi/bubble-bfdi.gif",
    "bubbleSize": 100,
    "task": {
      "bgColor": "rgba(77,243,255,1)",
      "borderColor": "#0b1384",
      "textColor": "#0c48c0",
      "fontSize": 20,
      "neon": false
    },
    "feedback": {
      "bgColor": "#131316",
      "borderColor": "#e67e22",
      "textColor": "#ffffff",
      "fontSize": 20,
      "neon": false
    }
  },
  "finalFeedback": "🎉 Well Done!",
  "feedbackImage": "https://media.tenor.com/E_UyRwJIOeAAAAAi/congrats-congratulations.gif",
  "feedbackEnabled": true,
  "feedbackMode": "image",
  "autoDistractors": false,
  "quizUseOtherCorrect": false,
  "quizMaxOptions": 4,
  "tasks": [
    {
      "question": "... the enchanted forest hide talking animals?",
      "correct": [
        "Does"
      ],
      "wrong": []
    },
    {
      "question": "The magic broom ... sweep the sky every day.",
      "correct": [
        "doesn’t"
      ],
      "wrong": []
    },
    {
      "question": "... the phoenix rise from ashes yesterday?",
      "correct": [
        "Did"
      ],
      "wrong": []
    },
    {
      "question": "The troll ... eat broccoli every day.",
      "correct": [
        "doesn’t"
      ],
      "wrong": []
    },
    {
      "question": "... the fairy godmother grant three wishes last week?",
      "correct": [
        "Did"
      ],
      "wrong": []
    },
    {
      "question": "The sleepy dragon ... guard the treasure yesterday.",
      "correct": [
        "didn’t"
      ],
      "wrong": []
    },
    {
      "question": "... unicorns eat rainbows every day?",
      "correct": [
        "Do"
      ],
      "wrong": []
    },
    {
      "question": "The spellbook ... open by itself every evening.",
      "correct": [
        "doesn’t"
      ],
      "wrong": []
    },
    {
      "question": "The ogre ... live in a candy house.",
      "correct": [
        "doesn’t"
      ],
      "wrong": []
    },
    {
      "question": "... the talking tree tell stories every morning?",
      "correct": [
        "Does"
      ],
      "wrong": []
    },
    {
      "question": "The cloud castle ... float away last summer.",
      "correct": [
        "didn’t"
      ],
      "wrong": []
    },
    {
      "question": "... the dragon breathe fire yesterday morning?",
      "correct": [
        "Did"
      ],
      "wrong": []
    },
    {
      "question": "Fairies ... use umbrellas when it rains.",
      "correct": [
        "don’t"
      ],
      "wrong": []
    },
    {
      "question": "... the magic mirror show the truth last night?",
      "correct": [
        "Did"
      ],
      "wrong": []
    },
    {
      "question": "The mermaid ... ride a seahorse to school.",
      "correct": [
        "doesn’t"
      ],
      "wrong": []
    },
    {
      "question": "... elves bake magic cookies on Sundays?",
      "correct": [
        "Do"
      ],
      "wrong": []
    },
    {
      "question": "The talking cat ... understand human words.",
      "correct": [
        "doesn’t"
      ],
      "wrong": []
    },
    {
      "question": "... the golden key unlock the treasure chest yesterday?",
      "correct": [
        "Did"
      ],
      "wrong": []
    },
    {
      "question": "The dragon ... whisper secrets every Tuesday.",
      "correct": [
        "doesn’t"
      ],
      "wrong": []
    },
    {
      "question": "... the troll cross the rainbow bridge?",
      "correct": [
        "Does"
      ],
      "wrong": []
    }
  ]
}